python_yaastar-0.2.dist-info/DESCRIPTION.rst
python_yaastar-0.2.dist-info/METADATA
python_yaastar-0.2.dist-info/RECORD
python_yaastar-0.2.dist-info/WHEEL
python_yaastar-0.2.dist-info/metadata.json
python_yaastar-0.2.dist-info/top_level.txt
yaastar/__init__.py
yaastar/amap.py
yaastar/astar.py
yaastar/heapset.py
yaastar/pyheapq.py
