Metadata-Version: 2.0
Name: python-yaastar
Version: 0.2
Summary: Yet another A-star graph search algorithm implementation
Home-page: https://github.com/kummahiih/python-yaastar
Author: Pauli Rikula
Author-email: pauli.rikula@gmail.com
License: See the source files
Platform: UNKNOWN
Classifier: License :: OSI Approved :: MIT License
Classifier: Programming Language :: Python :: 3.6
Requires-Python: ~=3.6
